dynpy/__init__.py
dynpy/bn.py
dynpy/bniterate.c
dynpy/bniterate.cpython-312-darwin.so
dynpy/bniterate.pyx
dynpy/ca.py
dynpy/caching.py
dynpy/cutils.c
dynpy/cutils.cpython-312-darwin.so
dynpy/cutils.pyx
dynpy/dynsys.py
dynpy/graphdynamics.py
dynpy/markov.py
dynpy/mx.py
dynpy/sample_nets.py
dynpy/utils.py
dynpy-0.3.0.dist-info/licenses/LICENSE.txt
dynpy-0.3.0.dist-info/METADATA
dynpy-0.3.0.dist-info/WHEEL
dynpy-0.3.0.dist-info/top_level.txt
dynpy-0.3.0.dist-info/RECORD
