Metadata-Version: 2.4
Name: dynpy
Version: 0.3.0
Summary: Dynamical systems for Python
Author-email: Artemy Kolchinsky <artemyk@gmail.com>
License-Expression: GPL-3.0-or-later
Project-URL: Homepage, https://github.com/artemyk/dynpy
Project-URL: Documentation, http://dynpy.readthedocs.org/
Project-URL: Download, https://github.com/artemyk/dynpy/tarball/master
Classifier: Development Status :: 3 - Alpha
Classifier: Intended Audience :: Science/Research
Classifier: Topic :: Scientific/Engineering
Classifier: Programming Language :: Python
Classifier: Programming Language :: Python :: 3
Requires-Python: >=3.8
License-File: LICENSE.txt
Requires-Dist: numpy>=1.6
Requires-Dist: scipy>=0.13
Requires-Dist: six>=1.8.0
Provides-Extra: test
Requires-Dist: coverage>=3.7.0; extra == "test"
Requires-Dist: sphinx>=1.0.0; extra == "test"
Requires-Dist: matplotlib; extra == "test"
Dynamic: license-file
